mlzutil/RELEASE-VERSION
mlzutil/__init__.py
mlzutil/validators.py
mlzutil/version.py
mlzutil-0.1.0.dist-info/DESCRIPTION.rst
mlzutil-0.1.0.dist-info/METADATA
mlzutil-0.1.0.dist-info/RECORD
mlzutil-0.1.0.dist-info/WHEEL
mlzutil-0.1.0.dist-info/metadata.json
mlzutil-0.1.0.dist-info/top_level.txt
