Metadata-Version: 2.0
Name: mlzutil
Version: 0.1.0
Summary: Useful common functionality by MLZ
Home-page: UNKNOWN
Author: Georg Brandl <g.brandl@fz-juelich.de>, Alexander Lenz <alexander.lenz@frm2.tum.de>
Author-email: alexander.lenz@frm2.tum.de
License: GPL
Platform: UNKNOWN
Classifier: Development Status :: 5 - Production/Stable
Classifier: Intended Audience :: Developers
Classifier: Natural Language :: English
Classifier: License :: OSI Approved :: GNU General Public License (GPL)
Classifier: Operating System :: OS Independent
Classifier: Programming Language :: Python
Classifier: Programming Language :: Python :: 2
Classifier: Programming Language :: Python :: 2.7
Classifier: Topic :: Software Development
Classifier: Topic :: Software Development :: Libraries :: Python Modules
Requires-Dist: numpy
